fastdds/_dummy.cpython-310-x86_64-linux-gnu.so
ros_fastdds-3.2.3.data/data/bin/fast-discovery-server
ros_fastdds-3.2.3.data/data/bin/fast-discovery-server-1.0.1
ros_fastdds-3.2.3.data/data/bin/fastdds
ros_fastdds-3.2.3.data/data/bin/ros-discovery
ros_fastdds-3.2.3.data/data/include/fastdds/LibrarySettings.hpp
ros_fastdds-3.2.3.data/data/include/fastdds/config.hpp
ros_fastdds-3.2.3.data/data/include/fastdds/fastdds_auto_link.hpp
ros_fastdds-3.2.3.data/data/include/fastdds/fastdds_dll.hpp
ros_fastdds-3.2.3.data/data/include/fastdds/config/doxygen_modules.hpp
ros_fastdds-3.2.3.data/data/include/fastdds/dds/builtin/topic/BuiltinTopicKey.hpp
ros_fastdds-3.2.3.data/data/include/fastdds/dds/builtin/topic/ParticipantBuiltinTopicData.hpp
ros_fastdds-3.2.3.data/data/include/fastdds/dds/builtin/topic/PublicationBuiltinTopicData.hpp
ros_fastdds-3.2.3.data/data/include/fastdds/dds/builtin/topic/SubscriptionBuiltinTopicData.hpp
ros_fastdds-3.2.3.data/data/include/fastdds/dds/builtin/topic/TopicBuiltinTopicData.hpp
ros_fastdds-3.2.3.data/data/include/fastdds/dds/common/InstanceHandle.hpp
ros_fastdds-3.2.3.data/data/include/fastdds/dds/core/Entity.hpp
ros_fastdds-3.2.3.data/data/include/fastdds/dds/core/LoanableArray.hpp
ros_fastdds-3.2.3.data/data/include/fastdds/dds/core/LoanableCollection.hpp
ros_fastdds-3.2.3.data/data/include/fastdds/dds/core/LoanableSequence.hpp
ros_fastdds-3.2.3.data/data/include/fastdds/dds/core/LoanableTypedCollection.hpp
ros_fastdds-3.2.3.data/data/include/fastdds/dds/core/ReturnCode.hpp
ros_fastdds-3.2.3.data/data/include/fastdds/dds/core/StackAllocatedSequence.hpp
ros_fastdds-3.2.3.data/data/include/fastdds/dds/core/Time_t.hpp
ros_fastdds-3.2.3.data/data/include/fastdds/dds/core/Types.hpp
ros_fastdds-3.2.3.data/data/include/fastdds/dds/core/UserAllocatedSequence.hpp
ros_fastdds-3.2.3.data/data/include/fastdds/dds/core/condition/Condition.hpp
ros_fastdds-3.2.3.data/data/include/fastdds/dds/core/condition/GuardCondition.hpp
ros_fastdds-3.2.3.dist-info/METADATA
ros_fastdds-3.2.3.dist-info/WHEEL
ros_fastdds-3.2.3.dist-info/top_level.txt
ros_fastdds-3.2.3.dist-info/RECORD
ros_fastdds-3.2.3.dist-info/licenses/LICENSE
