Metadata-Version: 2.4
Name: ros-fastdds
Version: 3.2.3
Summary: A ROS package providing the eProsima Fast DDS implementation for high-performance, real-time data distribution in ROS 2 systems.
License-File: LICENSE
Requires-Dist: ros-foonathan-memory-vendor~=1.3.1
Requires-Dist: ros-fastcdr~=2.3.3
Dynamic: description
Dynamic: description-content-type
Dynamic: license-file
Dynamic: requires-dist
Dynamic: summary
